README.md
setup.py
adamp/__init__.py
adamp/adamp.py
adamp/sgdp.py
adamp.egg-info/PKG-INFO
adamp.egg-info/SOURCES.txt
adamp.egg-info/dependency_links.txt
adamp.egg-info/top_level.txt