Metadata-Version: 2.1
Name: adamp
Version: 0.2.0
Summary: AdamP optimizer: Slowing Down the Weight Norm Increase in Momentum-based Optimizers
Home-page: https://github.com/clovaai/AdamP
Author: NAVER Corp.
License: UNKNOWN
Platform: UNKNOWN
Classifier: Programming Language :: Python :: 3
Classifier: License :: OSI Approved :: MIT License
Classifier: Operating System :: OS Independent
